utils/KinMS_figures.py
utils/__init__.py
utils/sauron_colormap.py
kinmspy_test-2.0.0.dist-info/LICENSE
kinmspy_test-2.0.0.dist-info/METADATA
kinmspy_test-2.0.0.dist-info/WHEEL
kinmspy_test-2.0.0.dist-info/top_level.txt
kinmspy_test-2.0.0.dist-info/RECORD
