Metadata-Version: 2.1
Name: kinmspy-test
Version: 2.0.0
Summary: Kinematic molecular simulation tool for astronomers
Home-page: https://github.com/NikkiZabel/KinMSpy
Author: KinMS_Team
Author-email: dawsonj5@cardiff.ac.uk
License: UNKNOWN
Platform: UNKNOWN
Classifier: Programming Language :: Python :: 3
Classifier: License :: OSI Approved :: MIT License
Classifier: Operating System :: OS Independent
Requires-Python: >=3.6
